[
  {
    "id": "1",
    "Дансны ангилал": "Мөнгө ба түүнтэй адилтгах",
    "Дансны дугаар": "10110",
    "Дансны нэр": "Касс дахь бэлэн мөнгө",
    "Валют": "MNT",
    "Тоолуур": "1"
  },
  {
    "id": "2",
    "Дансны ангилал": "Мөнгө ба түүнтэй адилтгах",
    "Дансны дугаар": "11110",
    "Дансны нэр": "Банкинд байршуулсан харилцах",
    "Валют": "MNT",
    "Тоолуур": "9"
  },
  {
    "id": "3",
    "Дансны ангилал": "Мөнгө, түүнтэй адилтгах хөрөнгө",
    "Дансны дугаар": "11111",
    "Дансны нэр": "Банкинд байршуулсан харилцах",
    "Валют": "USD",
    "Тоолуур": "3"
  },
  {
    "id": "4",
    "Дансны ангилал": "Мөнгө ба түүнтэй адилтгах",
    "Дансны дугаар": "11210",
    "Дансны нэр": "Банкинд байршуулсан хадгаламж",
    "Валют": "MNT",
    "Тоолуур": "1"
  },
  {
    "id": "5",
    "Дансны ангилал": "Дансны авлага",
    "Дансны дугаар": "12110",
    "Дансны нэр": "Борлуулалтын авлага",
    "Валют": "MNT",
    "Тоолуур": "1"
  },
  {
    "id": "6",
    "Дансны ангилал": "Дансны авлага",
    "Дансны дугаар": "12210",
    "Дансны нэр": "Байгууллагаас авах авлага",
    "Валют": "MNT",
    "Тоолуур": "1"
  },
  {
    "id": "7",
    "Дансны ангилал": "Дансны авлага",
    "Дансны дугаар": "12310",
    "Дансны нэр": "Хувь хүнээс авах авлага",
    "Валют": "MNT",
    "Тоолуур": "1"
  },
  {
    "id": "8",
    "Дансны ангилал": "Дансны авлага",
    "Дансны дугаар": "12410",
    "Дансны нэр": "Найдваргүй авлагын нөөц",
    "Валют": "MNT",
    "Тоолуур": "1"
  },
  {
    "id": "9",
    "Дансны ангилал": "Татвар, НДШ-ийн авлага",
    "Дансны дугаар": "13110",
    "Дансны нэр": "ААНОАТ-ын авлага",
    "Валют": "MNT",
    "Тоолуур": "1"
  },
  {
    "id": "10",
    "Дансны ангилал": "Татвар, НДШ-ийн авлага",
    "Дансны дугаар": "13210",
    "Дансны нэр": "ХАОАТ-ын авлага",
    "Валют": "MNT",
    "Тоолуур": "0"
  },
  {
    "id": "11",
    "Дансны ангилал": "Татвар, НДШ-ийн авлага",
    "Дансны дугаар": "13310",
    "Дансны нэр": "НӨАТ-ын авлага",
    "Валют": "MNT",
    "Тоолуур": "0"
  },
  {
    "id": "12",
    "Дансны ангилал": "Татвар, НДШ-ийн авлага",
    "Дансны дугаар": "13410",
    "Дансны нэр": "Бусад татварын авлага",
    "Валют": "MNT",
    "Тоолуур": "0"
  },
  {
    "id": "13",
    "Дансны ангилал": "Татвар, НДШ-ийн авлага",
    "Дансны дугаар": "13510",
    "Дансны нэр": "НДШ-ийн авлага",
    "Валют": "MNT",
    "Тоолуур": "0"
  },
  {
    "id": "14",
    "Дансны ангилал": "Бусад авлага",
    "Дансны дугаар": "14110",
    "Дансны нэр": "Хоорондын тооцооны авлага",
    "Валют": "MNT",
    "Тоолуур": "1"
  },
  {
    "id": "15",
    "Дансны ангилал": "Бусад авлага",
    "Дансны дугаар": "14210",
    "Дансны нэр": "Бусад авлага",
    "Валют": "MNT",
    "Тоолуур": "3"
  },
  {
    "id": "16",
    "Дансны ангилал": "Бусад санхүүгийн хөрөнгө",
    "Дансны дугаар": "15110",
    "Дансны нэр": "Арилжааны үнэт цаас",
    "Валют": "MNT",
    "Тоолуур": "1"
  },
  {
    "id": "17",
    "Дансны ангилал": "Бусад санхүүгийн хөрөнгө",
    "Дансны дугаар": "15210",
    "Дансны нэр": "Хөрөнгө оруулалтын үнэт цаас",
    "Валют": "MNT",
    "Тоолуур": "0"
  },
  {
    "id": "18",
    "Дансны ангилал": "Бусад санхүүгийн хөрөнгө",
    "Дансны дугаар": "15310",
    "Дансны нэр": "Үнэлгээний хасагдуулга",
    "Валют": "MNT",
    "Тоолуур": "0"
  },
  {
    "id": "19",
    "Дансны ангилал": "Зээл",
    "Дансны дугаар": "16210",
    "Дансны нэр": "Хувь хүнд олгосон зээл",
    "Валют": "MNT",
    "Тоолуур": "1"
  },
  {
    "id": "20",
    "Дансны ангилал": "Зээл",
    "Дансны дугаар": "16990",
    "Дансны нэр": "Эрсдлийн сангийн зардал",
    "Валют": "MNT",
    "Тоолуур": "0"
  },
  {
    "id": "21",
    "Дансны ангилал": "Бараа материал",
    "Дансны дугаар": "17110",
    "Дансны нэр": "Бараа материал",
    "Валют": "MNT",
    "Тоолуур": "1"
  },
  {
    "id": "22",
    "Дансны ангилал": "Урьдчилж төлсөн зардал/тооцоо",
    "Дансны дугаар": "17210",
    "Дансны нэр": "Урьдчилж төлсөн зардал/тооцоо",
    "Валют": "MNT",
    "Тоолуур": "1"
  },
  {
    "id": "23",
    "Дансны ангилал": "Бусад эргэлтийн хөрөнгө",
    "Дансны дугаар": "17310",
    "Дансны нэр": "Бусад эргэлтийн хөрөнгө",
    "Валют": "MNT",
    "Тоолуур": "1"
  },
  {
    "id": "24",
    "Дансны ангилал": "Борлуулах зорилгоор эзэмшиж буй эргэлтийн бус хөрөнгө (борлуулах бүлэг хөрөнгө)",
    "Дансны дугаар": "17410",
    "Дансны нэр": "БЗЭБ эргэлтийн бус хөрөнгө",
    "Валют": "MNT",
    "Тоолуур": "1"
  },
  {
    "id": "25",
    "Дансны ангилал": "Үндсэн хөрөнгө",
    "Дансны дугаар": "18000",
    "Дансны нэр": "Барилга",
    "Валют": "MNT",
    "Тоолуур": "1"
  },
  {
    "id": "26",
    "Дансны ангилал": "Үндсэн хөрөнгө",
    "Дансны дугаар": "18010",
    "Дансны нэр": "Барилгын хуримтлагдсан элэгдэл",
    "Валют": "MNT",
    "Тоолуур": "0"
  },
  {
    "id": "27",
    "Дансны ангилал": "Үндсэн хөрөнгө",
    "Дансны дугаар": "18110",
    "Дансны нэр": "Компьютер, тоног төхөөрөмж",
    "Валют": "MNT",
    "Тоолуур": "1"
  },
  {
    "id": "28",
    "Дансны ангилал": "Үндсэн хөрөнгө",
    "Дансны дугаар": "18120",
    "Дансны нэр": "Компьютер, тоног төхөөрөмжийн хуримтлагдсан элэгдэл",
    "Валют": "MNT",
    "Тоолуур": "1"
  },
  {
    "id": "29",
    "Дансны ангилал": "Үндсэн хөрөнгө",
    "Дансны дугаар": "18210",
    "Дансны нэр": "Тавилга, эд хогшил",
    "Валют": "MNT",
    "Тоолуур": "1"
  },
  {
    "id": "30",
    "Дансны ангилал": "Үндсэн хөрөнгө",
    "Дансны дугаар": "18220",
    "Дансны нэр": "Тавилга, эд хогшил хуримтлагдсан элэгдэл",
    "Валют": "MNT",
    "Тоолуур": "1"
  },
  {
    "id": "31",
    "Дансны ангилал": "Үндсэн хөрөнгө",
    "Дансны дугаар": "18310",
    "Дансны нэр": "Тээврийн хэрэгсэл",
    "Валют": "MNT",
    "Тоолуур": "1"
  },
  {
    "id": "32",
    "Дансны ангилал": "Үндсэн хөрөнгө",
    "Дансны дугаар": "18320",
    "Дансны нэр": "Тээврийн хэрэгсэлийн хуримтлагдсан элэгдэл",
    "Валют": "MNT",
    "Тоолуур": "1"
  },
  {
    "id": "33",
    "Дансны ангилал": "Үндсэн хөрөнгө",
    "Дансны дугаар": "18410",
    "Дансны нэр": "Бусад үндсэн хөрөнгө",
    "Валют": "MNT",
    "Тоолуур": "0"
  },
  {
    "id": "34",
    "Дансны ангилал": "Үндсэн хөрөнгө",
    "Дансны дугаар": "18510",
    "Дансны нэр": "Бусад үндсэн хөрөнгийн хуримтлагдсан элэгдэл",
    "Валют": "MNT",
    "Тоолуур": "0"
  },
  {
    "id": "34",
    "Дансны ангилал": "Биет бус хөрөнгө",
    "Дансны дугаар": "19000",
    "Дансны нэр": "Биет бус хөрөнгө",
    "Валют": "MNT",
    "Тоолуур": "1"
  },
  {
    "id": "35",
    "Дансны ангилал": "Биет бус хөрөнгө",
    "Дансны дугаар": "19010",
    "Дансны нэр": "Биет бус хөрөнгийн хуримтлагдсан элэгдэл",
    "Валют": "MNT",
    "Тоолуур": "1"
  },
  {
    "id": "36",
    "Дансны ангилал": "Биологийн хөрөнгө",
    "Дансны дугаар": "19110",
    "Дансны нэр": "Биологийн хөрөнгө",
    "Валют": "MNT",
    "Тоолуур": "0"
  },
  {
    "id": "37",
    "Дансны ангилал": "Урт хугацаат хөрөнгө оруулалт",
    "Дансны дугаар": "19120",
    "Дансны нэр": "Урт хугацаат хөрөнгө оруулалт",
    "Валют": "MNT",
    "Тоолуур": "0"
  },
  {
    "id": "38",
    "Дансны ангилал": "Хайгуул ба үнэлгээний хөрөнгө",
    "Дансны дугаар": "19130",
    "Дансны нэр": "Хайгуул ба үнэлгээний хөрөнгө",
    "Валют": "MNT",
    "Тоолуур": "0"
  },
  {
    "id": "39",
    "Дансны ангилал": "Хөрөнгө оруулалтын зориулалттай үл хөдлөх хөрөнгө",
    "Дансны дугаар": "19150",
    "Дансны нэр": "Хөрөнгө оруулалтын зориулалттай үл хөдлөх хөрөнгө",
    "Валют": "MNT",
    "Тоолуур": "0"
  },
  {
    "id": "40",
    "Дансны ангилал": "Бусад эргэлтийн бус хөрөнгө",
    "Дансны дугаар": "19160",
    "Дансны нэр": "Бусад эргэлтийн бус хөрөнгө",
    "Валют": "MNT",
    "Тоолуур": "0"
  },
  {
    "id": "41",
    "Дансны ангилал": "Дансны өглөг",
    "Дансны дугаар": "21110",
    "Дансны нэр": "Бэлтгэн нийлүүлэгчдэд өгөх өглөг",
    "Валют": "MNT",
    "Тоолуур": "0"
  },
  {
    "id": "42",
    "Дансны ангилал": "Дансны өглөг",
    "Дансны дугаар": "21120",
    "Дансны нэр": "Байгууллагад өгөх өглөг",
    "Валют": "MNT",
    "Тоолуур": "0"
  },
  {
    "id": "43",
    "Дансны ангилал": "Дансны өглөг",
    "Дансны дугаар": "21130",
    "Дансны нэр": "Хувь хүнд өгөх өглөг",
    "Валют": "MNT",
    "Тоолуур": "0"
  },
  {
    "id": "44",
    "Дансны ангилал": "Дансны өглөг",
    "Дансны дугаар": "21140",
    "Дансны нэр": "Санхүүгийн түрээсийн өглөг",
    "Валют": "MNT",
    "Тоолуур": "0"
  },
  {
    "id": "45",
    "Дансны ангилал": "Дансны өглөг",
    "Дансны дугаар": "21150",
    "Дансны нэр": "Бусад өглөг",
    "Валют": "MNT",
    "Тоолуур": "1"
  },
  {
    "id": "46",
    "Дансны ангилал": "Цалингийн өглөг",
    "Дансны дугаар": "22110",
    "Дансны нэр": "Цалингийн өглөг",
    "Валют": "MNT",
    "Тоолуур": "1"
  },
  {
    "id": "47",
    "Дансны ангилал": "Татварын өглөг",
    "Дансны дугаар": "22210",
    "Дансны нэр": "ААНОАТ-ын өглөг",
    "Валют": "MNT",
    "Тоолуур": "0"
  },
  {
    "id": "48",
    "Дансны ангилал": "Татварын өглөг",
    "Дансны дугаар": "22230",
    "Дансны нэр": "ХАОАТ-ын өглөг",
    "Валют": "MNT",
    "Тоолуур": "1"
  },
  {
    "id": "49",
    "Дансны ангилал": "Татварын өглөг",
    "Дансны дугаар": "22240",
    "Дансны нэр": "НӨАТ-ын өглөг",
    "Валют": "MNT",
    "Тоолуур": "2"
  },
  {
    "id": "50",
    "Дансны ангилал": "Татварын өглөг",
    "Дансны дугаар": "22250",
    "Дансны нэр": "Бусад татварын өглөг",
    "Валют": "MNT",
    "Тоолуур": "0"
  },
  {
    "id": "51",
    "Дансны ангилал": "НДШ-ийн өглөг",
    "Дансны дугаар": "23110",
    "Дансны нэр": "НДШ-ийн өглөг",
    "Валют": "MNT",
    "Тоолуур": "1"
  },
  {
    "id": "52",
    "Дансны ангилал": "Богино хугацаат зээл",
    "Дансны дугаар": "24110",
    "Дансны нэр": "Богино хугацаат зээл",
    "Валют": "MNT",
    "Тоолуур": "0"
  },
  {
    "id": "53",
    "Дансны ангилал": "Хүүний өглөг",
    "Дансны дугаар": "24210",
    "Дансны нэр": "Хүүний өглөг",
    "Валют": "MNT",
    "Тоолуур": "0"
  },
  {
    "id": "54",
    "Дансны ангилал": "Ногдол ашгийн өглөг",
    "Дансны дугаар": "25110",
    "Дансны нэр": "Ногдол ашгийн өглөг",
    "Валют": "MNT",
    "Тоолуур": "0"
  },
  {
    "id": "55",
    "Дансны ангилал": "Урьдчилж орсон орлого",
    "Дансны дугаар": "26110",
    "Дансны нэр": "Урьдчилж орсон орлого",
    "Валют": "MNT",
    "Тоолуур": "1"
  },
  {
    "id": "56",
    "Дансны ангилал": "Нөөц -өр төлбөр-",
    "Дансны дугаар": "26210",
    "Дансны нэр": "Нөөц -өр төлбөр-",
    "Валют": "MNT",
    "Тоолуур": "0"
  },
  {
    "id": "57",
    "Дансны ангилал": "Бусад богино хугацаат өр төлбөр",
    "Дансны дугаар": "26310",
    "Дансны нэр": "Бусад богино хугацаат өр төлбөр",
    "Валют": "MNT",
    "Тоолуур": "1"
  },
  {
    "id": "58",
    "Дансны ангилал": "Борлуулах зорилгоор эзэмшиж буй эргэлтийн бус хөрөнгө (борлуулах бүлэг хөрөнгө)-нд хамаарах өр төлбөр",
    "Дансны дугаар": "27110",
    "Дансны нэр": "Борлуулах зорилгоор эзэмшиж буй эргэлтийн бус хөрөнгө (борлуулах бүлэг хөрөнгө)-нд хамаарах өр төлбөр",
    "Валют": "MNT",
    "Тоолуур": "0"
  },
  {
    "id": "1",
    "Дансны ангилал": "Урт хугацаат зээл",
    "Дансны дугаар": "28110",
    "Дансны нэр": "Урт хугацаат зээл",
    "Валют": "MNT",
    "Тоолуур": "0"
  },
  {
    "id": "59",
    "Дансны ангилал": "Нөөц -өр төлбөр-",
    "Дансны дугаар": "28210",
    "Дансны нэр": "Урт хугацаат нөөц өр төлбөр",
    "Валют": "MNT",
    "Тоолуур": "0"
  },
  {
    "id": "60",
    "Дансны ангилал": "Хойшлогдсон татварын өр",
    "Дансны дугаар": "28310",
    "Дансны нэр": "Хойшлогдсон татварын өр",
    "Валют": "MNT",
    "Тоолуур": "0"
  },
  {
    "id": "61",
    "Дансны ангилал": "Бусад урт хугацаат өр төлбөр",
    "Дансны дугаар": "28410",
    "Дансны нэр": "Бусад урт хугацаат өр төлбөр",
    "Валют": "MNT",
    "Тоолуур": "10"
  },
  {
    "id": "62",
    "Дансны ангилал": "Бусад урт хугацаат өр төлбөр",
    "Дансны дугаар": "29000",
    "Дансны нэр": "ВАЛЮТЫН СПОТ ПОЗИЦИЙН ДАНС",
    "Валют": "MNT",
    "Тоолуур": "1"
  },
  {
    "id": "63",
    "Дансны ангилал": "Бусад урт хугацаат өр төлбөр",
    "Дансны дугаар": "29001",
    "Дансны нэр": "ВАЛЮТЫН СПОТ ПОЗИЦИЙН ДАНС",
    "Валют": "USD",
    "Тоолуур": "1"
  },
  {
    "id": "64",
    "Дансны ангилал": "Хувьцаат капитал",
    "Дансны дугаар": "31110",
    "Дансны нэр": "Төрийн өмч",
    "Валют": "MNT",
    "Тоолуур": "0"
  },
  {
    "id": "65",
    "Дансны ангилал": "Хувьцаат капитал",
    "Дансны дугаар": "31120",
    "Дансны нэр": "Хувийн өмч",
    "Валют": "MNT",
    "Тоолуур": "1"
  },
  {
    "id": "66",
    "Дансны ангилал": "Хувьцаат капитал",
    "Дансны дугаар": "31130",
    "Дансны нэр": "Хувьцаат",
    "Валют": "MNT",
    "Тоолуур": "0"
  },
  {
    "id": "67",
    "Дансны ангилал": "Халаасны хувьцаа",
    "Дансны дугаар": "32110",
    "Дансны нэр": "Халаасны хувьцаа",
    "Валют": "MNT",
    "Тоолуур": "0"
  },
  {
    "id": "68",
    "Дансны ангилал": "Нэмж төлөгдсөн капитал",
    "Дансны дугаар": "33110",
    "Дансны нэр": "Нэмж төлөгдсөн капитал",
    "Валют": "MNT",
    "Тоолуур": "0"
  },
  {
    "id": "69",
    "Дансны ангилал": "Хөрөнгийн дахин үнэлгээний нэмэгдэл",
    "Дансны дугаар": "34110",
    "Дансны нэр": "Хөрөнгийн дахин үнэлгээний нэмэгдэл",
    "Валют": "MNT",
    "Тоолуур": "0"
  },
  {
    "id": "70",
    "Дансны ангилал": "Гадаад валютын хөрвүүлэлтийн нөөц",
    "Дансны дугаар": "35110",
    "Дансны нэр": "Гадаад валютын хөрвүүлэлтийн нөөц",
    "Валют": "MNT",
    "Тоолуур": "0"
  },
  {
    "id": "70",
    "Дансны ангилал": "Эздийн өмчийн бусад хэсэг",
    "Дансны дугаар": "36110",
    "Дансны нэр": "Эздийн өмчийн бусад хэсэг",
    "Валют": "MNT",
    "Тоолуур": "0"
  },
  {
    "id": "71",
    "Дансны ангилал": "Хуримтлагдсан ашиг",
    "Дансны дугаар": "37110",
    "Дансны нэр": "Тухайн жилийн ашиг- алдагдал",
    "Валют": "MNT",
    "Тоолуур": "0"
  },
  {
    "id": "72",
    "Дансны ангилал": "Хуримтлагдсан ашиг",
    "Дансны дугаар": "37120",
    "Дансны нэр": "Өмнөх үеийн хуримтлагдсан ашиг- алдагдал",
    "Валют": "MNT",
    "Тоолуур": "1"
  },
  {
    "id": "73",
    "Дансны ангилал": "Хуримтлагдсан ашиг",
    "Дансны дугаар": "37130",
    "Дансны нэр": "Нөөцийн сан",
    "Валют": "MNT",
    "Тоолуур": "0"
  },
  {
    "id": "74",
    "Дансны ангилал": "Хуримтлагдсан ашиг",
    "Дансны дугаар": "37140",
    "Дансны нэр": "Нийгмийн хөгжлийн сан",
    "Валют": "MNT",
    "Тоолуур": "0"
  },
  {
    "id": "75",
    "Дансны ангилал": "Борлуулалтын орлого",
    "Дансны дугаар": "41110",
    "Дансны нэр": "Борлуулалтын орлого",
    "Валют": "MNT",
    "Тоолуур": "3"
  },
  {
    "id": "76",
    "Дансны ангилал": "Ногдол ашгийн орлого",
    "Дансны дугаар": "42120",
    "Дансны нэр": "Ногдол ашгийн орлого",
    "Валют": "MNT",
    "Тоолуур": "0"
  },
  {
    "id": "77",
    "Дансны ангилал": "Хүүгийн орлого",
    "Дансны дугаар": "43120",
    "Дансны нэр": "Бусад хүүгийн орлого",
    "Валют": "MNT",
    "Тоолуур": "2"
  },
  {
    "id": "78",
    "Дансны ангилал": "Валютын арилжааны орлого",
    "Дансны дугаар": "44110",
    "Дансны нэр": "Валютын арилжааны орлого",
    "Валют": "MNT",
    "Тоолуур": "1"
  },
  {
    "id": "79",
    "Дансны ангилал": "Ханшийн тэгшитгэлийн орлого",
    "Дансны дугаар": "44120",
    "Дансны нэр": "Ханшийн тэгшитгэлийн орлого",
    "Валют": "MNT",
    "Тоолуур": "1"
  },
  {
    "id": "80",
    "Дансны ангилал": "Бусад орлого",
    "Дансны дугаар": "45110",
    "Дансны нэр": "Бусад орлого",
    "Валют": "MNT",
    "Тоолуур": "0"
  },
  {
    "id": "81",
    "Дансны ангилал": "Үндсэн хөрөнгө данснаас хассаны олз",
    "Дансны дугаар": "45120",
    "Дансны нэр": "Үндсэн хөрөнгө данснаас хассаны олз",
    "Валют": "MNT",
    "Тоолуур": "0"
  },
  {
    "id": "82",
    "Дансны ангилал": "Биет бус хөрөнгө данснаас хассаны олз",
    "Дансны дугаар": "45130",
    "Дансны нэр": "Биет бус хөрөнгө данснаас хассаны олз",
    "Валют": "MNT",
    "Тоолуур": "0"
  },
  {
    "id": "83",
    "Дансны ангилал": "Хөрөнгө оруулалт борлуулснаас үүссэн олз",
    "Дансны дугаар": "45140",
    "Дансны нэр": "Хөрөнгө оруулалт борлуулснаас үүссэн гарз",
    "Валют": "MNT",
    "Тоолуур": "0"
  },
  {
    "id": "84",
    "Дансны ангилал": "Хөрөнгийн дахин үнэлгээний нэмэгдлийн зөрүү",
    "Дансны дугаар": "46110",
    "Дансны нэр": "Хөрөнгийн дахин үнэлгээний нэмэгдлийн зөрүү",
    "Валют": "MNT",
    "Тоолуур": "0"
  },
  {
    "id": "85",
    "Дансны ангилал": "Гадаад валютын хөрвүүлэлтийн зөрүү",
    "Дансны дугаар": "46120",
    "Дансны нэр": "Гадаад валютын хөрвүүлэлтийн зөрүү",
    "Валют": "MNT",
    "Тоолуур": "0"
  },
  {
    "id": "86",
    "Дансны ангилал": "Бусад олз (гарз)",
    "Дансны дугаар": "46130",
    "Дансны нэр": "Бусад олз (гарз)",
    "Валют": "MNT",
    "Тоолуур": "1"
  },
  {
    "id": "87",
    "Дансны ангилал": "Борлуулалтын өртөг",
    "Дансны дугаар": "50010",
    "Дансны нэр": "Борлуулалтын өртөг",
    "Валют": "MNT",
    "Тоолуур": "8"
  },
  {
    "id": "88",
    "Дансны ангилал": "Ерөнхий ба удирдлагын зардал",
    "Дансны дугаар": "51010",
    "Дансны нэр": "Цалингийн зардал",
    "Валют": "MNT",
    "Тоолуур": "1"
  },
  {
    "id": "89",
    "Дансны ангилал": "Ерөнхий ба удирдлагын зардал",
    "Дансны дугаар": "51020",
    "Дансны нэр": "Тэтгэмж, шагнал урамшуулал зардал",
    "Валют": "MNT",
    "Тоолуур": "0"
  },
  {
    "id": "90",
    "Дансны ангилал": "Ерөнхий ба удирдлагын зардал",
    "Дансны дугаар": "51030",
    "Дансны нэр": "Нийгмийн даатгалын зардал",
    "Валют": "MNT",
    "Тоолуур": "1"
  },
  {
    "id": "91",
    "Дансны ангилал": "Ерөнхий ба удирдлагын зардал",
    "Дансны дугаар": "51050",
    "Дансны нэр": "Сургалтын зардал",
    "Валют": "MNT",
    "Тоолуур": "1"
  },
  {
    "id": "92",
    "Дансны ангилал": "Ерөнхий ба удирдлагын зардал",
    "Дансны дугаар": "51060",
    "Дансны нэр": "Албан томилолтын зардал",
    "Валют": "MNT",
    "Тоолуур": "0"
  },
  {
    "id": "93",
    "Дансны ангилал": "Санхүүгийн зардал",
    "Дансны дугаар": "51070",
    "Дансны нэр": "Банкаар үйлчлүүлсэн шимтгэл хураамжийн зардал",
    "Валют": "MNT",
    "Тоолуур": "1"
  },
  {
    "id": "94",
    "Дансны ангилал": "Санхүүгийн зардал",
    "Дансны дугаар": "51071",
    "Дансны нэр": "Банкаар үйлчлүүлсэн шимтгэл хураамжийн зардал",
    "Валют": "USD",
    "Тоолуур": "1"
  },
  {
    "id": "95",
    "Дансны ангилал": "Санхүүгийн зардал",
    "Дансны дугаар": "52010",
    "Дансны нэр": "Зээлийн хүүгийн зардал",
    "Валют": "MNT",
    "Тоолуур": "0"
  },
  {
    "id": "96",
    "Дансны ангилал": "Санхүүгийн зардал",
    "Дансны дугаар": "52020",
    "Дансны нэр": "Аудитын төлбөр, мэргэжлийн үйлчилгээний зардал",
    "Валют": "MNT",
    "Тоолуур": "1"
  },
  {
    "id": "97",
    "Дансны ангилал": "Санхүүгийн зардал",
    "Дансны дугаар": "52030",
    "Дансны нэр": "Гишүүн, гишүүнчлэлийн хураамж",
    "Валют": "MNT",
    "Тоолуур": "0"
  },
  {
    "id": "98",
    "Дансны ангилал": "Санхүүгийн зардал",
    "Дансны дугаар": "52040",
    "Дансны нэр": "Даатгалын зардал",
    "Валют": "MNT",
    "Тоолуур": "0"
  },
  {
    "id": "99",
    "Дансны ангилал": "Ерөнхий ба удирдлагын зардал",
    "Дансны дугаар": "52050",
    "Дансны нэр": "Элэгдлийн зардал",
    "Валют": "MNT",
    "Тоолуур": "1"
  },
  {
    "id": "100",
    "Дансны ангилал": "Ерөнхий ба удирдлагын зардал",
    "Дансны дугаар": "52060",
    "Дансны нэр": "Түрээсийн зардал",
    "Валют": "MNT",
    "Тоолуур": "1"
  },
  {
    "id": "101",
    "Дансны ангилал": "Ерөнхий ба удирдлагын зардал",
    "Дансны дугаар": "52070",
    "Дансны нэр": "Засвар үйлчилгээ, хэрэглээний зардал",
    "Валют": "MNT",
    "Тоолуур": "1"
  },
  {
    "id": "102",
    "Дансны ангилал": "Ерөнхий ба удирдлагын зардал",
    "Дансны дугаар": "52080",
    "Дансны нэр": "Ашиглалтын зардал",
    "Валют": "MNT",
    "Тоолуур": "0"
  },
  {
    "id": "103",
    "Дансны ангилал": "Ерөнхий ба удирдлагын зардал",
    "Дансны дугаар": "52090",
    "Дансны нэр": "Бичиг хэргийн зардал",
    "Валют": "MNT",
    "Тоолуур": "1"
  },
  {
    "id": "104",
    "Дансны ангилал": "Ерөнхий ба удирдлагын зардал",
    "Дансны дугаар": "52100",
    "Дансны нэр": "Хамгаалалт, аюулгүй байдлын зардал",
    "Валют": "MNT",
    "Тоолуур": "0"
  },
  {
    "id": "105",
    "Дансны ангилал": "Ерөнхий ба удирдлагын зардал",
    "Дансны дугаар": "52110",
    "Дансны нэр": "Харилцаа холбооны зардал",
    "Валют": "MNT",
    "Тоолуур": "1"
  },
  {
    "id": "106",
    "Дансны ангилал": "Ерөнхий ба удирдлагын зардал",
    "Дансны дугаар": "52120",
    "Дансны нэр": "Тээвэр, шатахууны зардал",
    "Валют": "MNT",
    "Тоолуур": "1"
  },
  {
    "id": "107",
    "Дансны ангилал": "Ерөнхий ба удирдлагын зардал",
    "Дансны дугаар": "52130",
    "Дансны нэр": "Ариун цэврийн зардал",
    "Валют": "MNT",
    "Тоолуур": "0"
  },
  {
    "id": "108",
    "Дансны ангилал": "Ерөнхий ба удирдлагын зардал",
    "Дансны дугаар": "52140",
    "Дансны нэр": "Хөдөлмөр хамгаалал, галын аюулаас хамгаалах",
    "Валют": "MNT",
    "Тоолуур": "2"
  },
  {
    "id": "1",
    "Дансны ангилал": "Бусад зардал",
    "Дансны дугаар": "52160",
    "Дансны нэр": "ҮХХ татварын зардал",
    "Валют": "MNT",
    "Тоолуур": "0"
  },
  {
    "id": "1",
    "Дансны ангилал": "Борлуулалт, маркетингийн зардал",
    "Дансны дугаар": "52170",
    "Дансны нэр": "Маркетингийн зардал",
    "Валют": "MNT",
    "Тоолуур": "1"
  },
  {
    "id": "1",
    "Дансны ангилал": "Борлуулалт, маркетингийн зардал",
    "Дансны дугаар": "52171",
    "Дансны нэр": "Маркетингийн зардал",
    "Валют": "USD",
    "Тоолуур": "1"
  },
  {
    "id": "1",
    "Дансны ангилал": "Ерөнхий ба удирдлагын зардал",
    "Дансны дугаар": "52180",
    "Дансны нэр": "Найдваргүй авлагын зардал",
    "Валют": "MNT",
    "Тоолуур": "0"
  },
  {
    "id": "1",
    "Дансны ангилал": "Бусад зардал",
    "Дансны дугаар": "52190",
    "Дансны нэр": "Үндсэн ҮА-ний бусад",
    "Валют": "MNT",
    "Тоолуур": "1"
  },
  {
    "id": "1",
    "Дансны ангилал": "Валютын арилжааны зардал",
    "Дансны дугаар": "52200",
    "Дансны нэр": "Валютын арилжааны зардал",
    "Валют": "MNT",
    "Тоолуур": "1"
  },
  {
    "id": "1",
    "Дансны ангилал": "Валютын арилжааны зардал",
    "Дансны дугаар": "52201",
    "Дансны нэр": "Валют арилжааны зардал",
    "Валют": "USD",
    "Тоолуур": "1"
  },
  {
    "id": "1",
    "Дансны ангилал": "Ханшийн тэгшитгэлийн зардал",
    "Дансны дугаар": "52210",
    "Дансны нэр": "Ханшийн тэгшитгэлийн зардал",
    "Валют": "MNT",
    "Тоолуур": "1"
  },
  {
    "id": "1",
    "Дансны ангилал": "Үндсэн хөрөнгө данснаас хассаны гарз",
    "Дансны дугаар": "53010",
    "Дансны нэр": "Үндсэн хөрөнгө данснаас хассаны гарз",
    "Валют": "MNT",
    "Тоолуур": "0"
  },
  {
    "id": "1",
    "Дансны ангилал": "Биет бус хөрөнгө данснаас хассаны гарз",
    "Дансны дугаар": "53020",
    "Дансны нэр": "Биет бус хөрөнгө данснаас хассаны гарз",
    "Валют": "MNT",
    "Тоолуур": "0"
  },
  {
    "id": "1",
    "Дансны ангилал": "Хөрөнгө оруулалт борлуулснаас үүссэн олз (гарз)",
    "Дансны дугаар": "53030",
    "Дансны нэр": "Хөрөнгө оруулалт борлуулснаас үүссэн гарз",
    "Валют": "MNT",
    "Тоолуур": "0"
  },
  {
    "id": "1",
    "Дансны ангилал": "Бусад зардал",
    "Дансны дугаар": "53040",
    "Дансны нэр": "Зочин төлөөгчийн зардал",
    "Валют": "MNT",
    "Тоолуур": "0"
  },
  {
    "id": "1",
    "Дансны ангилал": "Бусад зардал",
    "Дансны дугаар": "53050",
    "Дансны нэр": "Баяр ёслол",
    "Валют": "MNT",
    "Тоолуур": "0"
  },
  {
    "id": "1",
    "Дансны ангилал": "Бусад зардал",
    "Дансны дугаар": "53060",
    "Дансны нэр": "Хандив",
    "Валют": "MNT",
    "Тоолуур": "0"
  },
  {
    "id": "1",
    "Дансны ангилал": "Бусад зардал",
    "Дансны дугаар": "53070",
    "Дансны нэр": "Торгууль",
    "Валют": "MNT",
    "Тоолуур": "0"
  },
  {
    "id": "1",
    "Дансны ангилал": "Бусад зардал",
    "Дансны дугаар": "53080",
    "Дансны нэр": "Валютын ханшны зөрүүгийн алдагдал",
    "Валют": "MNT",
    "Тоолуур": "0"
  },
  {
    "id": "1",
    "Дансны ангилал": "Бусад зардал",
    "Дансны дугаар": "53090",
    "Дансны нэр": "Ханшийн тэгшитгэлийн зардал",
    "Валют": "MNT",
    "Тоолуур": "0"
  },
  {
    "id": "1",
    "Дансны ангилал": "Бусад зардал",
    "Дансны дугаар": "53100",
    "Дансны нэр": "Үндсэн бус ҮА бусад зардал",
    "Валют": "MNT",
    "Тоолуур": "1"
  },
  {
    "id": "1",
    "Дансны ангилал": "Орлогын татварын зардал",
    "Дансны дугаар": "54110",
    "Дансны нэр": "Орлогын татварын зардал",
    "Валют": "MNT",
    "Тоолуур": "2"
  }
]